{
  "data": "2026-05-24",
  "total_jogos": 25,
  "selecoes": [
    {
      "market_id": "c67fe0c645091f98b370e803221fbb87",
      "event": "Hellas Verona vs AS Roma",
      "competition": "Serie A - Italy",
      "sport_key": "soccer_italy_serie_a",
      "start_time": "2026-05-24T18:45:00Z",
      "home_team": "Hellas Verona",
      "away_team": "AS Roma",
      "favorito": "AS Roma",
      "odd_favorito": 1.356,
      "odd_empate": 4.973,
      "odd_zebra": 9.05,
      "num_bookmakers": 24,
      "score": 84,
      "motivo": "Score 84/100 | 4/5 vitórias | 24 casas",
      "form_jogos_analisados": 5,
      "form_vitorias": 4,
      "form_media_gols_sofridos": 0.6
    },
    {
      "market_id": "cbf105caa5d11b7a821bf70c8eec9a89",
      "event": "Cremonese vs Como",
      "competition": "Serie A - Italy",
      "sport_key": "soccer_italy_serie_a",
      "start_time": "2026-05-24T18:45:00Z",
      "home_team": "Cremonese",
      "away_team": "Como",
      "favorito": "Como",
      "odd_favorito": 1.485,
      "odd_empate": 4.517,
      "odd_zebra": 6.495,
      "num_bookmakers": 24,
      "score": 90,
      "motivo": "Score 90/100 | 3/5 vitórias | 24 casas",
      "form_jogos_analisados": 5,
      "form_vitorias": 3,
      "form_media_gols_sofridos": 0.4
    },
    {
      "market_id": "bdd5478025348693f3832fce36316804",
      "event": "Columbus Crew SC vs Atlanta United FC",
      "competition": "MLS",
      "sport_key": "soccer_usa_mls",
      "start_time": "2026-05-24T21:00:00Z",
      "home_team": "Columbus Crew SC",
      "away_team": "Atlanta United FC",
      "favorito": "Columbus Crew SC",
      "odd_favorito": 1.531,
      "odd_empate": 4.392,
      "odd_zebra": 5.44,
      "num_bookmakers": 24,
      "score": 75,
      "motivo": "Score 75/100 | 0/5 vitórias | 24 casas",
      "form_jogos_analisados": 0,
      "form_vitorias": 0,
      "form_media_gols_sofridos": 0.0
    },
    {
      "market_id": "b526e8360f770b479c7be8ccd6a9b362",
      "event": "Inter Miami CF vs Philadelphia Union",
      "competition": "MLS",
      "sport_key": "soccer_usa_mls",
      "start_time": "2026-05-24T23:00:00Z",
      "home_team": "Inter Miami CF",
      "away_team": "Philadelphia Union",
      "favorito": "Inter Miami CF",
      "odd_favorito": 1.383,
      "odd_empate": 5.3,
      "odd_zebra": 6.484,
      "num_bookmakers": 24,
      "score": 71,
      "motivo": "Score 71/100 | 0/5 vitórias | 24 casas",
      "form_jogos_analisados": 0,
      "form_vitorias": 0,
      "form_media_gols_sofridos": 0.0
    }
  ]
}